[
  {
    "key": "dart",
    "name": "Dart SDK",
    "extension": ".dart",
    "icon": "https://cdn.jsdelivr.net/gh/devicons/devicon/icons/dart/dart-original.svg",
    "path": {
      "validation": "/bin/flutter",
      "hint": "/Users/your_username/flutter"
    },
    "snippet": "void main() {\n  print('Hello from Dart!');\n}",
    "supported": "supported",
    "need_sdk_path": true
  },
  {
    "key": "shell",
    "name": "Shell",
    "extension": ".sh",
    "icon": "https://img.icons8.com/ios/50/000000/console.png",
    "sdk_path": "/bin",
    "path": {
      "validation": "/bash",
      "hint": ""
    },
    "snippet": "#!/bin/bash\necho \"Hello from Shell\"",
    "supported": "supported",
    "need_sdk_path": true
  },
  {
    "key": "c",
    "name": "C",
    "extension": ".c",
    "icon": "https://cdn.jsdelivr.net/gh/devicons/devicon/icons/c/c-original.svg",
    "sdk_path": "/usr/bin",
    "path": {
      "validation": "/gcc",
      "hint": "/usr/bin/gcc"
    },
    "snippet": "#include <stdio.h>\n\nint main() {\n    printf(\"Hello from C!\\n\");\n    return 0;\n}",
    "supported": "supported",
    "need_sdk_path": true
  },
  {
    "key": "cpp",
    "name": "C++",
    "extension": ".cpp",
    "icon": "https://cdn.jsdelivr.net/gh/devicons/devicon/icons/cplusplus/cplusplus-original.svg",
    "sdk_path": "/usr/bin",
    "path": {
      "validation": "/g++",
      "hint": "/usr/bin/g++"
    },
    "snippet": "#include <iostream>\n\nint main() {\n    std::cout << \"Hello from C++!\" << std::endl;\n    return 0;\n}",
    "supported": "supported",
    "need_sdk_path": true
  },
  {
    "key": "py",
    "name": "Python",
    "extension": ".py",
    "icon": "https://cdn.jsdelivr.net/gh/devicons/devicon/icons/python/python-original.svg",
    "path": {
      "validation": "/python3",
      "hint": "/usr/local/bin/python3"
    },
    "snippet": "def main():\n    print(\"Hello from Python!\")\n\nif __name__ == \"__main__\":\n    main()",
    "supported": "upcoming",
    "need_sdk_path": true
  },
  {
    "key": "swift",
    "name": "Swift",
    "extension": ".swift",
    "icon": "https://cdn.jsdelivr.net/gh/devicons/devicon/icons/swift/swift-original.svg",
    "sdk_path": "/usr/bin",
    "path": {
      "validation": "/swift",
      "hint": "/usr/bin/swift"
    },
    "snippet": "import Foundation\n\nprint(\"Hello from Swift!\")",
    "supported": "supported",
    "need_sdk_path": true
  },
  {
    "key": "js",
    "name": "JavaScript",
    "extension": ".js",
    "icon": "https://cdn.jsdelivr.net/gh/devicons/devicon/icons/javascript/javascript-original.svg",
    "path": {
      "validation": "/node",
      "hint": "/usr/local/bin/node"
    },
    "snippet": "console.log(\"Hello from JavaScript!\");",
    "supported": "supported",
    "need_sdk_path": false
  },
  {
    "key": "html",
    "name": "HTML",
    "extension": ".html",
    "icon": "https://cdn.jsdelivr.net/gh/devicons/devicon/icons/html5/html5-original.svg",
    "path": {
      "validation": "",
      "hint": ""
    },
    "snippet": "<!DOCTYPE html>\n<html>\n<head>\n  <title>Hello HTML</title>\n</head>\n<body>\n  <h1>Hello from HTML!</h1>\n</body>\n</html>",
    "supported": "supported",
    "need_sdk_path": false
  },
  {
    "key": "css",
    "name": "CSS",
    "extension": ".css",
    "icon": "https://cdn.jsdelivr.net/gh/devicons/devicon/icons/css3/css3-original.svg",
    "path": {
      "validation": "",
      "hint": ""
    },
    "snippet": "body {\n  background-color: #f0f0f0;\n  color: #333;\n  font-family: sans-serif;\n}",
    "supported": "supported",
    "need_sdk_path": false
  },
  {
    "key": "json",
    "name": "JSON",
    "extension": ".json",
    "icon": "https://cdn.jsdelivr.net/gh/devicons/devicon/icons/json/json-original.svg",
    "path": {
      "validation": "",
      "hint": ""
    },
    "snippet": "{\n  \"key\": \"value\"\n}",
    "supported": "supported",
    "need_sdk_path": false
  },
  {
    "key": "xml",
    "name": "XML",
    "extension": ".xml",
    "icon": "https://cdn.jsdelivr.net/gh/devicons/devicon/icons/xml/xml-original.svg",
    "path": {
      "validation": "",
      "hint": ""
    },
    "snippet": "<root>\n  <element>Value</element>\n</root>",
    "supported": "supported",
    "need_sdk_path": false
  },
  {
    "key": "txt",
    "name": "Text File",
    "extension": ".txt",
    "icon": "",
    "path": {
      "validation": "",
      "hint": ""
    },
    "snippet": "",
    "supported": "supported",
    "need_sdk_path": false
  },
  {
    "key": "log",
    "name": "Log File",
    "extension": ".log",
    "icon": "",
    "path": {
      "validation": "",
      "hint": ""
    },
    "snippet": "",
    "supported": "supported",
    "need_sdk_path": false
  },
  {
    "key": "ai",
    "name": "AI Response",
    "extension": ".ai",
    "icon": "",
    "path": {
      "validation": "",
      "hint": ""
    },
    "snippet": "",
    "supported": "supported",
    "need_sdk_path": false
  }
]